app/__init__.py
app/api.py
app/core.py
app/monitoring.py
app/strategies.py
app/web3utils.py
apptronik_autopilot-0.1.0.dist-info/licenses/LICENSE
tests/__init__.py
tests/test_api.py
tests/test_core.py
tests/test_web3utils.py
apptronik_autopilot-0.1.0.dist-info/METADATA
apptronik_autopilot-0.1.0.dist-info/WHEEL
apptronik_autopilot-0.1.0.dist-info/top_level.txt
apptronik_autopilot-0.1.0.dist-info/RECORD
