Metadata-Version: 2.4
Name: apptronik-autopilot
Version: 0.1.0
Summary: AI-powered autopilot protocol for Web3 and DeFi
Home-page: https://github.com/Apptronik-AI/autopilot
Author: Apptronik AI
Author-email: support@apptronik-ai.org
License: MIT
Classifier: Programming Language :: Python :: 3
Classifier: License :: OSI Approved :: MIT License
Classifier: Operating System :: OS Independent
Requires-Python: >=3.8
License-File: LICENSE
Requires-Dist: web3
Requires-Dist: requests
Requires-Dist: python-dotenv
Requires-Dist: cryptography
Requires-Dist: fastapi
Requires-Dist: uvicorn
Requires-Dist: prometheus_client
Dynamic: author
Dynamic: author-email
Dynamic: classifier
Dynamic: description
Dynamic: description-content-type
Dynamic: home-page
Dynamic: license
Dynamic: license-file
Dynamic: requires-dist
Dynamic: requires-python
Dynamic: summary
